plover_italian_stentura.py
plover_italian_stentura-0.5.6.dist-info/DESCRIPTION.rst
plover_italian_stentura-0.5.6.dist-info/METADATA
plover_italian_stentura-0.5.6.dist-info/RECORD
plover_italian_stentura-0.5.6.dist-info/WHEEL
plover_italian_stentura-0.5.6.dist-info/entry_points.txt
plover_italian_stentura-0.5.6.dist-info/metadata.json
plover_italian_stentura-0.5.6.dist-info/top_level.txt
plover_italian_stentura-0.5.6.dist-info/zip-safe
