Metadata-Version: 2.0
Name: plover-italian-stentura
Version: 0.5.6
Summary: Italian Stentura support for Plover
Home-page: https://github.com/benoit-pierre/plover_italian_stentura
Author: Benoit Pierre
Author-email: benoit.pierre@gmail.com
License: GNU General Public License v2 or later (GPLv2+)
Keywords: plover plover_plugin
Platform: UNKNOWN
Classifier: Development Status :: 4 - Beta
Classifier: Environment :: Plugins
Classifier: Intended Audience :: End Users/Desktop
Classifier: License :: OSI Approved :: GNU General Public License v2 or later (GPLv2+)
Classifier: Operating System :: OS Independent
Classifier: Programming Language :: Python :: 3
Classifier: Programming Language :: Python :: 3.4
Classifier: Programming Language :: Python :: 3.5
Classifier: Programming Language :: Python :: 3.6
Requires-Dist: plover (>=4.0.0.dev6)
